odoo/addons/product_pricelist_fixed_discount/LICENSE
odoo/addons/product_pricelist_fixed_discount/README.rst
odoo/addons/product_pricelist_fixed_discount/__init__.py
odoo/addons/product_pricelist_fixed_discount/__manifest__.py
odoo/addons/product_pricelist_fixed_discount/images/screen.png
odoo/addons/product_pricelist_fixed_discount/models/__init__.py
odoo/addons/product_pricelist_fixed_discount/models/product_pricelist.py
odoo/addons/product_pricelist_fixed_discount/readme/CONTRIBUTORS.md
odoo/addons/product_pricelist_fixed_discount/readme/DESCRIPTION.md
odoo/addons/product_pricelist_fixed_discount/readme/USAGE.md
odoo/addons/product_pricelist_fixed_discount/static/description/icon.png
odoo/addons/product_pricelist_fixed_discount/static/description/index.html
odoo/addons/product_pricelist_fixed_discount/tests/TEST_INTSTRUCTIONS.rst
odoo/addons/product_pricelist_fixed_discount/views/product_pricelist.xml
odoo_addon_product_pricelist_fixed_discount-18.0.1.0.0.dist-info/METADATA
odoo_addon_product_pricelist_fixed_discount-18.0.1.0.0.dist-info/WHEEL
odoo_addon_product_pricelist_fixed_discount-18.0.1.0.0.dist-info/top_level.txt
odoo_addon_product_pricelist_fixed_discount-18.0.1.0.0.dist-info/RECORD
